html5validator/__init__.py
html5validator/cli.py
html5validator/validator.py
html5validator_2-1.1.5.dist-info/licenses/LICENSE
vnujar/CHANGELOG.md
vnujar/LICENSE
vnujar/README.md
vnujar/__init__.py
vnujar/vnu.jar
vnujar/vnu.jar.sha1
vnujar/vnu.jar.sha1.asc
html5validator_2-1.1.5.dist-info/METADATA
html5validator_2-1.1.5.dist-info/WHEEL
html5validator_2-1.1.5.dist-info/entry_points.txt
html5validator_2-1.1.5.dist-info/top_level.txt
html5validator_2-1.1.5.dist-info/RECORD
