Metadata-Version: 2.4
Name: html5validator-2
Version: 1.1.5
Summary: Validate HTML5 files.
Author-email: Cyb3rJak3 <git@cyberjake.xyz>
License-Expression: MIT
Project-URL: Homepage, https://github.com/Cyb3r-Jak3/html5validator-2
Project-URL: issues, https://github.com/Cyb3r-Jak3/html5validator/issues
Classifier: Development Status :: 5 - Production/Stable
Classifier: Intended Audience :: Developers
Classifier: Intended Audience :: Science/Research
Classifier: Natural Language :: English
Classifier: Operating System :: OS Independent
Classifier: Programming Language :: Python
Classifier: Programming Language :: Python :: 3.13
Classifier: Programming Language :: Python :: 3.12
Classifier: Programming Language :: Python :: 3.11
Classifier: Programming Language :: Python :: 3.10
Classifier: Programming Language :: Python :: 3.6
Classifier: Programming Language :: Python :: 3.7
Classifier: Programming Language :: Python :: 3.8
Classifier: Programming Language :: Python :: 3.9
Classifier: Programming Language :: Python :: Implementation :: PyPy
Requires-Python: >=3.8
License-File: LICENSE
Requires-Dist: PyYAML
Dynamic: license-file
